devopstoolsdaven/__init__.py
devopstoolsdaven/container.py
devopstoolsdaven/main.py
devopstoolsdaven/common/__init__.py
devopstoolsdaven/common/config.py
devopstoolsdaven/reports/__init__.py
devopstoolsdaven/reports/logger.py
devopstoolsdaven/reports/logging_processor.py
devopstoolsdaven/reports/report.py
devopstoolsdaven/templates/__init__.py
devopstoolsdaven/templates/templates.py
devopstoolsdaven/utils/__init__.py
devopstoolsdaven/utils/read_ini.py
devopstoolsdaven/utils/read_setup.py
devopstoolsdaven/vault/__init__.py
devopstoolsdaven/vault/vault.py
devopstoolsdaven/vault/vault_fake.py
devopstoolsdaven/vault/vault_little.py
devops_tools_daven-0.0.14.dist-info/LICENSE
devops_tools_daven-0.0.14.dist-info/METADATA
devops_tools_daven-0.0.14.dist-info/WHEEL
devops_tools_daven-0.0.14.dist-info/top_level.txt
devops_tools_daven-0.0.14.dist-info/RECORD
