Metadata-Version: 2.1
Name: devops-tools-daven
Version: 0.0.14
Summary: devops base library dist
Home-page: https://github.com/davengeo/devops-tools
Author: David Navarro Alvarez
Author-email: me@davengeo.com
License: UNKNOWN
Platform: UNKNOWN
Classifier: Development Status :: 4 - Beta
Classifier: License :: OSI Approved :: European Union Public Licence 1.2 (EUPL 1.2)
Classifier: Programming Language :: Python :: 3.8
Classifier: Topic :: System :: Systems Administration
License-File: LICENSE
Requires-Dist: argparse
Requires-Dist: chevron
Requires-Dist: cloudevents
Requires-Dist: json-spec
Requires-Dist: invoke
Requires-Dist: pyramda
Requires-Dist: PyYAML
Requires-Dist: fluent-logger
Requires-Dist: prometheus-client
Requires-Dist: dependency-injector (<5.0,>=4.0)
Requires-Dist: devopsprocessor-ifn (==0.1.0)
